zuper_typing.cpython-310-x86_64-linux-gnu.so
zuper_typing.pyi
zuper_typing_z7-7.3.2202211150.dist-info/WHEEL
zuper_typing_z7-7.3.2202211150.dist-info/top_level.txt
zuper_typing_z7-7.3.2202211150.dist-info/RECORD
zuper_typing_z7-7.3.2202211150.dist-info/METADATA
zuper_typing_z7-7.3.2202211150.dist-info/zip-safe
